obsfind/__init__.py
obsfind/create_output.py
obsfind/ephemeris.py
obsfind/make_pdfs.py
obsfind/outfmt.py
obsfind/plotting.py
obsfind/read_inputs.py
obsfind/run.py
pyobsfind-1.0.0.dist-info/licenses/LICENSE
pyobsfind-1.0.0.dist-info/METADATA
pyobsfind-1.0.0.dist-info/WHEEL
pyobsfind-1.0.0.dist-info/top_level.txt
pyobsfind-1.0.0.dist-info/RECORD
