Metadata-Version: 2.4
Name: pyObsFind
Version: 1.0.0
Summary: Package to find when solar system objects are observable
Author: Richard Cannon, Abigail Patrick, Ottavia Truttero
License: MIT
Keywords: astronomy,ephemeris,asteroids,comets
License-File: LICENSE
Requires-Dist: matplotlib
Requires-Dist: astropy
Requires-Dist: pandas
Requires-Dist: astroquery
Requires-Dist: rich
Requires-Dist: pylatex
Requires-Dist: ephem
Requires-Dist: pypdf
Requires-Dist: reportlab
Dynamic: license-file
